pydus/__init__.py
pydus/core.py
pydus-0.1.12.dist-info/METADATA
pydus-0.1.12.dist-info/WHEEL
pydus-0.1.12.dist-info/entry_points.txt
pydus-0.1.12.dist-info/top_level.txt
pydus-0.1.12.dist-info/RECORD
