Metadata-Version: 2.2
Name: pydus
Version: 0.1.12
Summary: CSV reader utility
Author-email: redlion <your.email@example.com>
License: MIT
Project-URL: Homepage, https://github.com/redlion/pydus
Project-URL: Issues, https://github.com/redlion/pydus/issues
Keywords: python,help,documentation,claude,ai
Classifier: Development Status :: 4 - Beta
Classifier: Intended Audience :: Developers
Classifier: License :: OSI Approved :: MIT License
Classifier: Programming Language :: Python :: 3
Classifier: Programming Language :: Python :: 3.8
Classifier: Programming Language :: Python :: 3.9
Classifier: Programming Language :: Python :: 3.10
Classifier: Topic :: Software Development :: Libraries :: Python Modules
Requires-Python: >=3.8
Requires-Dist: requests>=2.25.0
Requires-Dist: click>=8.0.0
